sloteq/__init__.py
sloteq/__main__.py
sloteq/tests/__init__.py
sloteq/tests/test_1984.py
sloteq-0.0.0.dev0.dist-info/LICENSE.txt
sloteq-0.0.0.dev0.dist-info/METADATA
sloteq-0.0.0.dev0.dist-info/WHEEL
sloteq-0.0.0.dev0.dist-info/top_level.txt
sloteq-0.0.0.dev0.dist-info/RECORD
