Metadata-Version: 2.2
Name: sloteq
Version: 0.0.0.dev0
Summary: sloteq
Author-email: Johannes <johannes-programming@mailfence.com>
License: The MIT License (MIT)
Project-URL: Download, https://pypi.org/project/sloteq/#files
Project-URL: Index, https://pypi.org/project/sloteq/
Project-URL: Source, https://github.com/johannes-programming/sloteq/
Classifier: Development Status :: 1 - Planning
Classifier: License :: OSI Approved :: MIT License
Classifier: Natural Language :: English
Classifier: Operating System :: OS Independent
Classifier: Programming Language :: Python
Classifier: Programming Language :: Python :: 3
Classifier: Programming Language :: Python :: 3 :: Only
Requires-Python: >=3.12.7
License-File: LICENSE.txt
